{
  "students": [
    {
      "id": "7557",
      "firstName": "Charlie",
      "lastName": "Brown",
      "email": "cb@mail3.com",
      "createdAt": "2024-10-25T01:53:16.789Z"
    },
    {
      "id": "tQP3",
      "firstName": "Carlos ",
      "lastName": "Hidalgo",
      "email": "carlos@gmail.com",
      "createdAt": "2024-10-26T00:42:04.889Z"
    },
    {
      "id": "AAHf",
      "firstName": "Gera",
      "lastName": "Meneses",
      "email": "gera@gmail.com",
      "createdAt": "2024-10-28T21:42:37.989Z"
    },
    {
      "id": "j18n",
      "firstName": "Mario",
      "lastName": "Hidalgo",
      "email": "mario@gmail.com",
      "createdAt": "2024-10-28T22:11:21.713Z"
    }
  ],
  "users": [
    {
      "id": "0381",
      "email": "admin@mail.com",
      "firstName": "admin",
      "lastName": "admin",
      "createdAt": "2024-10-25T01:53:16.789Z",
      "password": "123456",
      "token": "abcdefghlkasjdlasjdlsakjdlsakjdlsad123456"
    }
  ]
}